{
  "users": [
    {
      "userId": "1234",
      "userPw": "1234",
      "id": "da66bc0b-abc0-496e-b595-ec7317f38f6f"
    },
    {
      "userId": "5678",
      "userPw": "5678",
      "id": "3fb8e820-70fa-42c7-814e-67bd3bbf1586"
    }
  ],
  "todos": [
    {
      "userId": "1234",
      "todoId": "0000",
      "todo": "react"
    },
    {
      "userId": "1234",
      "todoId": "2222",
      "todo": "spring"
    },
    {
      "userId": "5678",
      "todoId": "1111",
      "todo": "java"
    },
    {
      "userId": "1",
      "todoId": "0000",
      "todo": "react"
    }
  ]
}
